openmol/__init__.py
openmol/amber_parm7.py
openmol/charge_lib.py
openmol/core.py
openmol/lammps_full.py
openmol/lammps_qmag.py
openmol/mapping.py
openmol/pdb.py
openmol/psf.py
openmol/tripos_mol2.py
openmol/utils.py
openmol-1.2.2.dist-info/LICENSE
openmol-1.2.2.dist-info/METADATA
openmol-1.2.2.dist-info/WHEEL
openmol-1.2.2.dist-info/top_level.txt
openmol-1.2.2.dist-info/RECORD
