Metadata-Version: 2.1
Name: openmol
Version: 1.2.2
Summary: Convert between popular molecular dynamics data file formats.
Author-email: Akhlak Mahmood <akhlakm@gatech.edu>
Project-URL: Homepage, https://github.com/akhlakm/OpenMOL
Project-URL: Bug Tracker, https://github.com/akhlakm/OpenMOL/issues
Keywords: research,simulation,development
Classifier: Operating System :: OS Independent
Classifier: Programming Language :: Python :: 3
Classifier: License :: OSI Approved :: MIT License
Requires-Python: >=3.0
License-File: LICENSE
